pytiny/__init__.py
pytiny-0.0.1.dist-info/LICENSE
pytiny-0.0.1.dist-info/METADATA
pytiny-0.0.1.dist-info/WHEEL
pytiny-0.0.1.dist-info/top_level.txt
pytiny-0.0.1.dist-info/RECORD
