Metadata-Version: 2.1
Name: pytiny
Version: 0.0.1
Summary: PyTiny is an in-memory key–value database written in Python.
Home-page: https://gitlab.com/azael_rguez/pytiny
Author: Alvaro Azael Rodriguez Rodriguez
Author-email: azael.rguez96@gmail.com
License: MIT
Platform: UNKNOWN
Classifier: Programming Language :: Python :: 3
Classifier: License :: OSI Approved :: MIT License
Classifier: Operating System :: OS Independent
Requires-Python: >=3.6
